quantylab/systrader/__init__.py
quantylab/systrader/util.py
quantylab/systrader/creon/__init__.py
quantylab/systrader/creon/_creon.py
quantylab/systrader/creon/auth.py
quantylab/systrader/creon/bridge_django.py
quantylab/systrader/creon/bridge_flask.py
quantylab/systrader/creon/constants.py
quantylab/systrader/creon/pub.py
quantylab/systrader/kiwoom/__init__.py
quantylab/systrader/kiwoom/_kiwoom.py
quantylab/systrader/kiwoom/bridge_tornado/__init__.py
quantylab/systrader/kiwoom/bridge_tornado/kiwoom_restful.py
quantylab/systrader/kiwoom/bridge_tornado/kiwoom_restful_client.py
quantylab/systrader/kiwoom/bridge_tornado/wait7am.py
quantylab/systrader/xing/__init__.py
quantylab/systrader/xing/env.py
quantylab/systrader/xing/model.py
quantylab/systrader/xing/provision.py
quantylab/systrader/xing/query.py
quantylab/systrader/xing/real.py
quantylab/systrader/xing/session.py
quantylab/systrader/xing/settings.py
quantylab/systrader/xing/res/__init__.py
quantylab/systrader/xing/res/parser.py
systrader-1.0.dist-info/LICENSE
systrader-1.0.dist-info/METADATA
systrader-1.0.dist-info/WHEEL
systrader-1.0.dist-info/top_level.txt
systrader-1.0.dist-info/RECORD
